<?xml version="1.0" encoding="UTF-8" ?>
<pets>
    <pet>
        <name>Buddy</name>
        <age>3</age>
        <birthdate>2022-04-15</birthdate>
        <type>Dog</type>
        <user>1</user>
    </pet>
    <pet>
        <name>Mittens</name>
        <age>5</age>
        <birthdate>2019-07-10</birthdate>
        <type>Cat</type>
        <user>3</user>
    </pet>
    <pet>
        <name>Charlie</name>
        <age>2</age>
        <birthdate>2023-01-05</birthdate>
        <type>Rabbit</type>
        <user>5</user>
    </pet>
    <pet>
        <name>Goldie</name>
        <age>1</age>
        <birthdate>2024-06-20</birthdate>
        <type>Fish</type>
        <user>8</user>
    </pet>
    <pet>
        <name>Luna</name>
        <age>4</age>
        <birthdate>2020-11-12</birthdate>
        <type>Dog</type>
        <user>7</user>
    </pet>
    <pet>
        <name>Shadow</name>
        <age>6</age>
        <birthdate>2018-09-03</birthdate>
        <type>Cat</type>
        <user>4</user>
    </pet>
    <pet>
        <name>Daisy</name>
        <age>3</age>
        <birthdate>2022-05-18</birthdate>
        <type>Parrot</type>
        <user>6</user>
    </pet>
    <pet>
        <name>Bella</name>
        <age>7</age>
        <birthdate>2016-02-25</birthdate>
        <type>Dog</type>
        <user>2</user>
    </pet>
    <pet>
        <name>Oreo</name>
        <age>4</age>
        <birthdate>2020-08-14</birthdate>
        <type>Hamster</type>
        <user>9</user>
    </pet>
    <pet>
        <name>Max</name>
        <age>2</age>
        <birthdate>2023-03-22</birthdate>
        <type>Dog</type>
        <user>1</user>
    </pet>
    <pet>
        <name>Ruby</name>
        <age>5</age>
        <birthdate>2019-12-01</birthdate>
        <type>Cat</type>
        <user>1</user>
    </pet>
    <pet>
        <name>Sunny</name>
        <age>1</age>
        <birthdate>2024-07-30</birthdate>
        <type>Turtle</type>
        <user>3</user>
    </pet>
    <pet>
        <name>Simba</name>
        <age>6</age>
        <birthdate>2018-06-25</birthdate>
        <type>Dog</type>
        <user>4</user>
    </pet>
    <pet>
        <name>Peaches</name>
        <age>3</age>
        <birthdate>2022-09-17</birthdate>
        <type>Cat</type>
        <user>7</user>
    </pet>
    <pet>
        <name>Bubbles</name>
        <age>2</age>
        <birthdate>2023-10-09</birthdate>
        <type>Fish</type>
        <user>5</user>
    </pet>
</pets>